wiki_random/__init__.py
wiki_random/wiki.py
wiki_random-0.1.5.dist-info/WHEEL
wiki_random-0.1.5.dist-info/METADATA
wiki_random-0.1.5.dist-info/RECORD
