Metadata-Version: 2.1
Name: wiki-random
Version: 0.1.5
Summary: get random article from wikipedia
Home-page: https://github.com/Ezykill/wiki_random
Author: Igor Moryto
Author-email: 56959606+Ezykill@users.noreply.github.com
Requires-Python: >=3.10,<4.0
Classifier: Programming Language :: Python :: 3
Classifier: Programming Language :: Python :: 3.10
Requires-Dist: bs4 (>=0.0.1,<0.0.2)
Requires-Dist: requests (>=2.28.1,<3.0.0)
Project-URL: Repository, https://github.com/Ezykill/wiki_random
